blockchyp/__init__.py
blockchyp/blockchyp.py
blockchyp/cache.py
blockchyp/error.py
blockchyp/types.py
blockchyp/util.py
blockchyp/version.py
blockchyp/crypto/__init__.py
blockchyp/crypto/auth.py
blockchyp/crypto/certificate.py
blockchyp/crypto/symmetric.py
blockchyp/resources/blockchyp.crt
blockchyp-2.28.1.post1.dist-info/LICENSE
blockchyp-2.28.1.post1.dist-info/METADATA
blockchyp-2.28.1.post1.dist-info/WHEEL
blockchyp-2.28.1.post1.dist-info/top_level.txt
blockchyp-2.28.1.post1.dist-info/zip-safe
blockchyp-2.28.1.post1.dist-info/RECORD
