Metadata-Version: 2.1
Name: blockchyp
Version: 2.28.1.post1
Summary: The official library for accessing the BlockChyp Terminal and Gateway APIs
Home-page: https://github.com/blockchyp/blockchyp-python
Author: BlockChyp
Author-email: support@blockchyp.com
License: MIT
Platform: UNKNOWN
Classifier: Intended Audience :: Developers
Classifier: License :: OSI Approved :: MIT License
Classifier: Natural Language :: English
Classifier: Programming Language :: Python
Classifier: Programming Language :: Python :: 3
Classifier: Programming Language :: Python :: 3.5
Classifier: Programming Language :: Python :: 3.6
Classifier: Programming Language :: Python :: 3.7
Classifier: Programming Language :: Python :: 3.8
Classifier: Topic :: Software Development :: Libraries
Requires-Python: >=3.5
License-File: LICENSE
Requires-Dist: cryptography
Requires-Dist: requests
